era5cli/__init__.py
era5cli/__version__.py
era5cli/_request_size.py
era5cli/cli.py
era5cli/fetch.py
era5cli/info.py
era5cli/inputref.py
era5cli/key_management.py
era5cli/utils.py
era5cli/args/__init__.py
era5cli/args/common.py
era5cli/args/config.py
era5cli/args/info.py
era5cli/args/periods.py
era5cli-2.0.1.dist-info/METADATA
era5cli-2.0.1.dist-info/WHEEL
era5cli-2.0.1.dist-info/entry_points.txt
era5cli-2.0.1.dist-info/licenses/LICENSE
era5cli-2.0.1.dist-info/RECORD
