Metadata-Version: 2.4
Name: era5cli
Version: 2.0.1
Summary: A command line interface to download ERA5 data from the Copernicus Climate Data Store. https://climate.copernicus.eu/..
Author: Ronald van Haren, Jaro Camphuijsen, Yifat Dzigan, Niels Drost, Fakhereh Alidoost, Bouwe Andela, Jerom Aerts, Berend Weel, Rolf Hut, Klaus Zimmermann, Peter Kalverla, Aytaç Paçal, Stef Smeets, Stefan Verhoeven, Elizaveta Malinina
Author-email: Barbara Vreede <b.vreede@esciencecenter.nl>, Bart Schilperoort <b.schilperoort@esciencecenter.nl>
License: Apache Software License
License-File: LICENSE
Keywords: ERA-5,cds api,cds download,climate data
Classifier: Development Status :: 5 - Production/Stable
Classifier: Intended Audience :: Developers
Classifier: Intended Audience :: Science/Research
Classifier: License :: OSI Approved :: Apache Software License
Classifier: Natural Language :: English
Classifier: Operating System :: MacOS :: MacOS X
Classifier: Operating System :: Microsoft :: Windows
Classifier: Operating System :: POSIX
Classifier: Programming Language :: Python
Classifier: Programming Language :: Python :: 3 :: Only
Classifier: Programming Language :: Python :: 3.9
Classifier: Programming Language :: Python :: 3.10
Classifier: Programming Language :: Python :: 3.11
Classifier: Programming Language :: Python :: 3.12
Classifier: Programming Language :: Python :: 3.13
Classifier: Topic :: Scientific/Engineering :: Atmospheric Science
Requires-Python: >=3.9
Requires-Dist: cdsapi>=0.7.4
Requires-Dist: netcdf4
Requires-Dist: pathos
Requires-Dist: ptable
Provides-Extra: dev
Requires-Dist: black; extra == 'dev'
Requires-Dist: bump-my-version; extra == 'dev'
Requires-Dist: flake8; extra == 'dev'
Requires-Dist: flake8-pyproject; extra == 'dev'
Requires-Dist: hatch; extra == 'dev'
Requires-Dist: isort; extra == 'dev'
Requires-Dist: pytest; extra == 'dev'
Requires-Dist: pytest-cov; extra == 'dev'
Requires-Dist: pytest-flake8; extra == 'dev'
Provides-Extra: docs
Requires-Dist: mkdocs; extra == 'docs'
Requires-Dist: mkdocs-gen-files; extra == 'docs'
Requires-Dist: mkdocs-material; extra == 'docs'
